metayaml/__init__.py
metayaml/exception.py
metayaml/jinja_eval.py
metayaml/metayaml.py
metayaml_ng-1.2.dist-info/LICENSE
metayaml_ng-1.2.dist-info/METADATA
metayaml_ng-1.2.dist-info/WHEEL
metayaml_ng-1.2.dist-info/top_level.txt
metayaml_ng-1.2.dist-info/RECORD
