Metadata-Version: 2.1
Name: metayaml-ng
Version: 1.2
Summary: Enhancements of yaml format to support include and python expression
Download-URL: https://pypi.org/project/metayaml-ng/
Author: Anton Tagunov
Maintainer: William Barnhart
Maintainer-email: williambbarnhart@gmail.com
Classifier: Programming Language :: Python :: 3
Classifier: Development Status :: 4 - Beta
Classifier: Intended Audience :: Developers
Classifier: Natural Language :: English
Classifier: License :: OSI Approved :: MIT License
Classifier: Environment :: Other Environment
Classifier: Operating System :: OS Independent
Classifier: Topic :: Software Development :: Libraries :: Python Modules
License-File: LICENSE
Requires-Dist: jinja2 (>=3.0)
Requires-Dist: PyYAML
